cromulent/__init__.py
cromulent/extract.py
cromulent/model.py
cromulent/multiple_instantiation.py
cromulent/reader.py
cromulent/reader_old.py
cromulent/vocab.py
cromulent/data/crm-profile.json
cromulent/data/crm_vocab.tsv
cromulent/data/key_order.json
cromulent/data/linked-art.json
cromulent/data/overrides.json
cromulent/data/vocab_classes.json
cromulent/data/vocab_instances.json
cromulent-1.0.1.dist-info/LICENSE
cromulent-1.0.1.dist-info/METADATA
cromulent-1.0.1.dist-info/WHEEL
cromulent-1.0.1.dist-info/top_level.txt
cromulent-1.0.1.dist-info/RECORD
