Metadata-Version: 2.2
Name: cromulent
Version: 1.0.1
Summary: A library for mapping CIDOC-CRM (v7.1) classes to Python objects
Home-page: https://github.com/linked-art/crom
Author: Rob Sanderson
Author-email: robert.sanderson@yale.edu
Classifier: Programming Language :: Python
Classifier: Programming Language :: Python :: 3
Classifier: License :: OSI Approved :: Apache Software License
Classifier: Development Status :: 3 - Alpha
Classifier: Intended Audience :: Developers
Classifier: Operating System :: OS Independent
Classifier: Topic :: Software Development :: Libraries :: Python Modules
License-File: LICENSE
Requires-Dist: rdflib
Requires-Dist: PyLD
Dynamic: author
Dynamic: author-email
Dynamic: classifier
Dynamic: home-page
Dynamic: requires-dist
Dynamic: summary
